{"capabilities":{"capabilities":{"serviceLevel":"Cloud","teamTrainedAiRemote":{"createdAt":"2021-11-15T22:19:13.566Z","url":"https://d2277bbe-60b1-423a-a44e-33df1447c001.ts9-c.com"}},"subscriptions":[{"type":"team","id":"d2277bbe-60b1-423a-a44e-33df1447c001","name":"Nils Jonsson's Team","isAdmin":true,"isPaid":true,"members":1,"defaultTeam":true,"isExpired":false}],"userProfile":"NewPro"},"signature":"10edd7b0ed43d36198c1afbeb482e1a6ab5e45d084b4e929eea348e13e698a01","creation_time":"2021-11-17T23:54:42.491524783Z"}